zenbot/__init__.py
zenbot/app.py
zenbot/zencyclopedia.py
zenbot-1.0.1.dist-info/LICENSE
zenbot-1.0.1.dist-info/WHEEL
zenbot-1.0.1.dist-info/METADATA
zenbot-1.0.1.dist-info/RECORD
