Metadata-Version: 2.1
Name: zenbot
Version: 1.0.1
Summary: The Zen of Python in Slack
License: MIT
Author: Bence Nagy
Author-email: bence@underyx.me
Requires-Python: >=3.6,<4.0
Classifier: License :: OSI Approved :: MIT License
Classifier: Programming Language :: Python :: 3
Classifier: Programming Language :: Python :: 3.6
Classifier: Programming Language :: Python :: 3.7
Classifier: Programming Language :: Python :: 3.8
Classifier: Programming Language :: Python :: 3.9
Requires-Dist: aiohttp (>=3.7.4,<4.0.0)
Requires-Dist: gunicorn (>=20.1.0,<21.0.0)
